{
  "player": {
    "id": 1,
    "name": "username"
  },
  "historyScore": {
    "id": 1,
    "scores": [
      {
        "tiempo": "00:01",
        "pulsasiones": 10,
        "ppm": 556,
        "wpm": 111,
        "errores": "0 (0%)"
      },
      {
        "tiempo": "00:01",
        "pulsasiones": 10,
        "ppm": 531,
        "wpm": 106,
        "errores": "0 (0%)"
      },
      {
        "tiempo": "00:01",
        "pulsasiones": 10,
        "ppm": 514,
        "wpm": 102,
        "errores": "0 (0%)"
      },
      {
        "tiempo": "00:01",
        "pulsasiones": 10,
        "ppm": 435,
        "wpm": 87,
        "errores": "0 (0%)"
      },
      {
        "tiempo": "00:02",
        "pulsasiones": 13,
        "ppm": 308,
        "wpm": 47,
        "errores": "1 (10%)"
      },
      {
        "tiempo": "00:02",
        "pulsasiones": 11,
        "ppm": 275,
        "wpm": 50,
        "errores": "0 (0%)"
      }
    ],
    "scoresDay": [{
        "tiempo": "00:02",
        "pulsasiones": 13,
        "ppm": 308,
        "wpm": 47,
        "errores": "1 (10%)"
      },
      {
        "tiempo": "00:02",
        "pulsasiones": 11,
        "ppm": 275,
        "wpm": 50,
        "errores": "0 (0%)"
      }]
  }
}